<?xml version="1.0" encoding="utf-8"?>
<!DOCTYPE hibernate-mapping PUBLIC "-//Hibernate/Hibernate Mapping DTD 3.0//EN"
"http://hibernate.sourceforge.net/hibernate-mapping-3.0.dtd">
<!-- 
    Mapping file autogenerated by MyEclipse Persistence Tools
-->
<hibernate-mapping>
    <class name="com.jovision.domain.TbAppVersion" table="tb_app_version" catalog="DeviceDB">
        <id name="id" type="java.lang.Integer">
            <column name="id" />
            <generator class="native" />
        </id>
        <property name="version" type="java.lang.String">
            <column name="version" length="30" not-null="true">
                <comment>app版本号</comment>
            </column>
        </property>
        <property name="versionValue" type="java.lang.Integer">
            <column name="version_value" not-null="true">
                <comment>app版本号对应值，用于版本比较</comment>
            </column>
        </property>
        <property name="url" type="java.lang.String">
            <column name="url" length="100" not-null="true">
                <comment>下载地址</comment>
            </column>
        </property>
        <property name="publishTime" type="java.sql.Timestamp">
            <column name="publish_time" length="19" not-null="true">
                <comment>发布时间</comment>
            </column>
        </property>
        <property name="appKey" type="java.lang.Integer">
            <column name="app_key">
                <comment>区分不同的软件</comment>
            </column>
        </property>
        <property name="updateLog" type="java.lang.String">
            <column name="update_log" length="65535">
                <comment>升级日志</comment>
            </column>
        </property>
        <property name="forceUpdate" type="java.lang.Boolean">
            <column name="force_update">
                <comment>是不是强制更新</comment>
            </column>
        </property>
        <property name="language" type="java.lang.String">
            <column name="language" length="20" not-null="true">
                <comment>语言</comment>
            </column>
        </property>
    </class>
</hibernate-mapping>
